{"naam":"Testnaam Test","rank":1,"point":{"points":10000},"isAdmin":false,"puntVerandering":[],"weeklyPointsObtained":false,"PreSets":[{},{},{},{},{}],"username":"Test","password":"Test","filiaal":"Apeldoorn"}
{"naam":"Testnaam Wouter","rank":2,"point":{"points":2101},"isAdmin":false,"puntVerandering":[{"puntVerandering":-330,"datum":{"year":2022,"month":5,"dayOfMonth":11,"hourOfDay":13,"minute":28,"second":30}},{"puntVerandering":-19,"datum":{"year":2022,"month":5,"dayOfMonth":12,"hourOfDay":17,"minute":58,"second":6}},{"puntVerandering":-50,"datum":{"year":2022,"month":5,"dayOfMonth":12,"hourOfDay":17,"minute":58,"second":16}}],"weeklyPointsObtained":false,"PreSets":[{},{},{},{},{}],"username":"jyn","password":"test","filiaal":"Delft"}
{"naam":"Testnaam Eric","rank":3,"point":{"points":2000},"isAdmin":false,"puntVerandering":[],"weeklyPointsObtained":false,"PreSets":[{},{},{},{},{}],"username":"Eric","password":"Bull","filiaal":"Den Haag"}
{"naam":"Testnaam Lucas","rank":4,"point":{"points":1500},"isAdmin":false,"puntVerandering":[],"weeklyPointsObtained":false,"PreSets":[{},{},{},{},{}],"username":"Lucas","password":"Clavel","filiaal":"Utrecht"}
{"naam":"Testnaam Damnn...Daniël","rank":5,"point":{"points":1000},"isAdmin":false,"puntVerandering":[],"weeklyPointsObtained":false,"PreSets":[{},{},{},{},{}],"username":"Wessel","password":"Horsthuis","filiaal":"Eindhoven"}
{"naam":"Testnaam Burton","rank":6,"point":{"points":20},"isAdmin":false,"puntVerandering":[],"weeklyPointsObtained":false,"PreSets":[{},{},{},{},{}],"username":"Burton","password":"Braam","filiaal":"Rotterdam HQ"}
